node_ec2_instance/__init__.py
node_ec2_instance/py.typed
node_ec2_instance/_jsii/__init__.py
node_ec2_instance/_jsii/cdk-node-ec2-instance@0.0.7.jsii.tgz
node_ec2_instance-0.0.7.dist-info/LICENSE
node_ec2_instance-0.0.7.dist-info/METADATA
node_ec2_instance-0.0.7.dist-info/WHEEL
node_ec2_instance-0.0.7.dist-info/top_level.txt
node_ec2_instance-0.0.7.dist-info/RECORD
