Metadata-Version: 2.1
Name: node-ec2-instance
Version: 0.0.7
Summary: CDK construct library for creating an EC2 instance with Node.js installed
Home-page: https://github.com/badmintoncryer/cdk-node-ec2-instance.git
Author: Kazuho CryerShinozuka<malaysia.cryer@gmail.com>
License: Apache-2.0
Project-URL: Source, https://github.com/badmintoncryer/cdk-node-ec2-instance.git
Classifier: Intended Audience :: Developers
Classifier: Operating System :: OS Independent
Classifier: Programming Language :: JavaScript
Classifier: Programming Language :: Python :: 3 :: Only
Classifier: Programming Language :: Python :: 3.8
Classifier: Programming Language :: Python :: 3.9
Classifier: Programming Language :: Python :: 3.10
Classifier: Programming Language :: Python :: 3.11
Classifier: Typing :: Typed
Classifier: Development Status :: 5 - Production/Stable
Classifier: License :: OSI Approved
Requires-Python: ~=3.8
License-File: LICENSE
Requires-Dist: aws-cdk-lib <3.0.0,>=2.143.0
Requires-Dist: constructs <11.0.0,>=10.0.5
Requires-Dist: jsii <2.0.0,>=1.101.0
Requires-Dist: publication >=0.0.3
Requires-Dist: typeguard ~=2.13.3
